{
    "airfield_cargo1": 2,
    "airfield_cargo2": 2,
    "airfield_cargo3": 2,
    "army_fuel_tank_01": 10,
    "army_fuel_tank_02": 20,
    "army_office_01": 25,
    "army_office_02": 25,
    "army_office_03": 25,
    "barrack_01": 25,
    "barrack_02": 25,
    "barrack_03": 25,
    "barrack_04": 25,
    "barrack_05": 25,
    "bir_jifjafa_afb_terminal": 30,
    "bulk_ship": 75,
    "car_bridge_2line": 75,
    "car_bridge_2line-1": 75,
    "car_bridge_2line-2": 75,
    "car_bridge_2line-3": 75,
    "cargo_ship": 125,
    "container_40ft": 2,
    "container_40ft_1": 2,
    "container_40ft_2": 2,
    "egypt_hangar_01": 75,
    "egypt_hangar_02": 75,
    "egypt_hangar_03": 75,
    "egypt_hangar_04": 75,
    "egypt_hangar_05": 75,
    "egypt_hangar_06": 75,
    "egypt_hangar_07": 75,
    "egypt_hangar_08": 75,
    "factory_01": 75,
    "factory_02": 25,
    "factory_03": 25,
    "factory_04": 50,
    "factory_05": 50,
    "factory_06": 50,
    "factory_07": 25,
    "factory_08": 25,
    "factory_09": 25,
    "factory_10": 50,
    "factory_11": 25,
    "factory_12": 25,
    "factory_13": 100,
    "fuel_tank_01": 25,
    "fuel_tank_02": 75,
    "fuel_tank_03": 50,
    "fuel_tank_04": 25,
    "gantry_crane": 15,
    "gas_administration_01": 50,
    "gas_generator_building_01": 100,
    "gas_pipe_01": 50,
    "gas_pipe_02": 50,
    "gas_pipe_03": 50,
    "gas_water_cooling_01": 35,
    "hangar_01": 25,
    "harbor_crane": 45,
    "helipad_01": 40,
    "israel_hangar_01": 25,
    "israel_hangar_02": 25,
    "kdp": 100,
    "pipe_set_01": 25,
    "pipe_set_02": 25,
    "power_station_01": 20,
    "power_station_02": 20,
    "reading_power_station": 250,
    "solar_field_element": 2,
    "substation_01": 10,
    "tank_hangar_01": 20,
    "tank_hangar_02": 20,
    "tank_hangar_03": 20,
    "warehouse_01": 25,
    "warehouse_02": 25,
    "warehouse_03": 25,
    "workshop_01": 75,
    "workshop_02": 75,
    "infantry ak": 25,
    "zil-135": 100,
    "nats_radar_01": 150,
    "rota_airport_small_building": 100,
    "tube_pile": 25,
    "industrial_container_01": 25,
    "industrial_container_02": 25,
    "industrial_container_03": 25,
    "airfield_building_tech_d": 50,
    "industrial_shed_01": 50,
    "outpost_hd": 100,
    "sandbag_13": 50,
    "antenna": 100,
    "cargo1": 25,
    "cargo2": 25,
    "cargo3": 25,
    "hesco_generator": 75,
    "container_generator": 75,
    "open_hangar_2": 100,
    "open_hangar_1": 100,
    "military_installation_3_withoutpalette": 100,
    "undegraund_shelter": 100,
    "military_installation_1": 100,
    "military_installation_2": 100,
    "military_installation_3": 100,
    "military_installation_4": 100,
    "military_installation_5": 150,
    "silo_01": 100,
    "silo_02": 100,
    "silo_03": 100,
    "undegraund_shelter2": 100,
    "hesco_watchtower_1": 75,
    "hesco_watchtower_2": 75,
    "hesco_watchtower_3": 75,
    "tent01": 25,
    "tent02": 25,
    "tent03": 25,
    "tent04": 25,
    "tent05": 25,
    "building01_pbr": 100,
    "building02_pbr": 100,
    "building03_pbr": 100,
    "building04_pbr": 100,
    "shelter02": 50,
    "shelter01": 50
}